impfeature/__init__.py
impfeature/featureimportance.py
impfeature-0.0.1.dist-info/LICENSE.txt
impfeature-0.0.1.dist-info/METADATA
impfeature-0.0.1.dist-info/WHEEL
impfeature-0.0.1.dist-info/top_level.txt
impfeature-0.0.1.dist-info/RECORD
